abcde/__init__.py
abcde/main.py
abcde/xxx.py
src/__init__.py
src/abc/__init__.py
src/abc/xxx.py
src/abcde/__init__.py
src/abcde/xxx.py
trust_spec_gen/__init__.py
trust_spec_gen/main.py
trust_spec_gen-0.1.1.dist-info/METADATA
trust_spec_gen-0.1.1.dist-info/WHEEL
trust_spec_gen-0.1.1.dist-info/entry_points.txt
trust_spec_gen-0.1.1.dist-info/top_level.txt
trust_spec_gen-0.1.1.dist-info/RECORD
