Metadata-Version: 2.1
Name: trust-spec-gen
Version: 0.1.1
Summary: UNKNOWN
Home-page: UNKNOWN
License: UNKNOWN
Platform: UNKNOWN
Requires-Dist: argparse
